{
  "robots": {
    "robot01": [
      {
        "serial_number": "89842464938132807891107743411894425287652211619",
        "issued_at": "2025-10-17T10:46:17.939356",
        "expires_at": "2025-10-17T10:56:17+00:00",
        "cert_path": "C:\\Users\\abhis\\Desktop\\Iris_project\\pki_poc\\app\\pki\\robot01.cert.pem",
        "status": "inactive"
      },
      {
        "serial_number": "194621946934771628038840861901456894444117839293",
        "issued_at": "2025-10-17T10:51:33.249267",
        "expires_at": "2025-10-17T11:01:33+00:00",
        "cert_path": "C:\\Users\\abhis\\Desktop\\Iris_project\\pki_poc\\app\\pki\\robot01.cert.pem",
        "status": "inactive"
      },
      {
        "serial_number": "507476652681852982420927575708635297002086069527",
        "issued_at": "2025-10-17T10:56:54.009005",
        "expires_at": "2025-10-17T11:06:54+00:00",
        "cert_path": "C:\\Users\\abhis\\Desktop\\Iris_project\\pki_poc\\app\\pki\\robot01.cert.pem",
        "status": "inactive"
      },
      {
        "serial_number": "160322425703647130664594197556338199788480030024",
        "issued_at": "2025-10-17T11:02:14.765710",
        "expires_at": "2025-10-17T11:12:14+00:00",
        "cert_path": "C:\\Users\\abhis\\Desktop\\Iris_project\\pki_poc\\app\\pki\\robot01.cert.pem",
        "status": "inactive"
      },
      {
        "serial_number": "357180249741641996729682551484171608124133046603",
        "issued_at": "2025-10-17T11:07:37.500509",
        "expires_at": "2025-10-17T11:17:37+00:00",
        "cert_path": "C:\\Users\\abhis\\Desktop\\Iris_project\\pki_poc\\app\\pki\\robot01.cert.pem",
        "status": "inactive"
      },
      {
        "serial_number": "113180025632215560817773895716450848911033922383",
        "issued_at": "2025-10-17T11:13:00.205540",
        "expires_at": "2025-10-17T11:23:00+00:00",
        "cert_path": "C:\\Users\\abhis\\Desktop\\Iris_project\\pki_poc\\app\\pki\\robot01.cert.pem",
        "status": "inactive"
      },
      {
        "serial_number": "511010243884716473572518324964854934434009520335",
        "issued_at": "2025-10-17T11:18:20.980499",
        "expires_at": "2025-10-17T11:28:20+00:00",
        "cert_path": "C:\\Users\\abhis\\Desktop\\Iris_project\\pki_poc\\app\\pki\\robot01.cert.pem",
        "status": "inactive"
      },
      {
        "serial_number": "711367470324118356306784970805566668015530282550",
        "issued_at": "2025-10-17T11:23:43.479229",
        "expires_at": "2025-10-17T11:33:43+00:00",
        "cert_path": "C:\\Users\\abhis\\Desktop\\Iris_project\\pki_poc\\app\\pki\\robot01.cert.pem",
        "status": "inactive"
      },
      {
        "serial_number": "77958677041706981923867265011670315944188818951",
        "issued_at": "2025-10-17T11:29:04.920233",
        "expires_at": "2025-10-17T11:39:04+00:00",
        "cert_path": "C:\\Users\\abhis\\Desktop\\Iris_project\\pki_poc\\app\\pki\\robot01.cert.pem",
        "status": "inactive"
      },
      {
        "serial_number": "74099661253129439964713448791514520515877221491",
        "issued_at": "2025-10-17T11:34:25.051828",
        "expires_at": "2025-10-17T11:44:25+00:00",
        "cert_path": "C:\\Users\\abhis\\Desktop\\Iris_project\\pki_poc\\app\\pki\\robot01.cert.pem",
        "status": "inactive"
      },
      {
        "serial_number": "454572528874860299394312283853204455641247543866",
        "issued_at": "2025-10-17T11:39:25.761985",
        "expires_at": "2025-10-17T11:49:25+00:00",
        "cert_path": "C:\\Users\\abhis\\Desktop\\Iris_project\\pki_poc\\app\\pki\\robot01.cert.pem",
        "status": "inactive"
      },
      {
        "serial_number": "115050543637658296640040755506239493930410027850",
        "issued_at": "2025-10-17T11:44:27.008245",
        "expires_at": "2025-10-17T11:54:26+00:00",
        "cert_path": "C:\\Users\\abhis\\Desktop\\Iris_project\\pki_poc\\app\\pki\\robot01.cert.pem",
        "status": "active"
      }
    ]
  },
  "servers": {},
  "brokers": {}
}